system_query/__init__.py
system_query/__main__.py
system_query/_version.py
system_query/all_info.py
system_query/available_features.py
system_query/cpu_info.py
system_query/errors.py
system_query/gpu_info.py
system_query/hdd_info.py
system_query/host_info.py
system_query/main.py
system_query/os_info.py
system_query/py.typed
system_query/query.py
system_query/ram_info.py
system_query/software_info.py
system_query/swap_info.py
system_query-0.4.1.dist-info/licenses/LICENSE
system_query-0.4.1.dist-info/licenses/NOTICE
system_query-0.4.1.dist-info/METADATA
system_query-0.4.1.dist-info/WHEEL
system_query-0.4.1.dist-info/top_level.txt
system_query-0.4.1.dist-info/RECORD
