Metadata-Version: 2.4
Name: system-query
Version: 0.4.1
Summary: Comprehensive and concise system information querying tool.
Home-page: https://github.com/mbdevpl/system-query
Download-URL: 
Author: Aleksandr Drozd, Emil Vatai, Mateusz Bysiek
Author-email: mateusz.bysiek@gmail.com
Maintainer: Mateusz Bysiek
Maintainer-email: mateusz.bysiek@gmail.com
License-Expression: Apache-2.0
Keywords: system,software,hardware
Classifier: Development Status :: 3 - Alpha
Classifier: Environment :: Console
Classifier: Intended Audience :: Developers
Classifier: Intended Audience :: Science/Research
Classifier: Natural Language :: English
Classifier: Operating System :: MacOS
Classifier: Operating System :: Microsoft :: Windows
Classifier: Operating System :: POSIX :: Linux
Classifier: Programming Language :: Python :: 3.9
Classifier: Programming Language :: Python :: 3.10
Classifier: Programming Language :: Python :: 3.11
Classifier: Programming Language :: Python :: 3.12
Classifier: Programming Language :: Python :: 3.13
Classifier: Programming Language :: Python :: 3 :: Only
Classifier: Topic :: System :: Hardware
Classifier: Topic :: System :: Monitoring
Classifier: Topic :: System :: Operating System
Classifier: Topic :: System :: Systems Administration
Classifier: Topic :: Utilities
Classifier: Typing :: Typed
Requires-Python: >=3.9
License-File: LICENSE
License-File: NOTICE
Requires-Dist: boilerplates[logging]~=1.2
Requires-Dist: version-query~=1.5
Provides-Extra: all
Requires-Dist: psutil~=7.0; extra == "all"
Requires-Dist: pint~=0.22; extra == "all"
Requires-Dist: py-cpuinfo~=9.0; extra == "all"
Requires-Dist: numpy>=1.6; extra == "all"
Requires-Dist: pycuda>=2022.1; extra == "all"
Requires-Dist: pyudev~=0.24.0; extra == "all"
Requires-Dist: psutil~=7.0; extra == "all"
Provides-Extra: cpu
Requires-Dist: psutil~=7.0; extra == "cpu"
Requires-Dist: pint~=0.22; extra == "cpu"
Requires-Dist: py-cpuinfo~=9.0; extra == "cpu"
Provides-Extra: gpu
Requires-Dist: numpy>=1.6; extra == "gpu"
Requires-Dist: pycuda>=2022.1; extra == "gpu"
Provides-Extra: hdd
Requires-Dist: pyudev~=0.24.0; extra == "hdd"
Provides-Extra: ram
Requires-Dist: psutil~=7.0; extra == "ram"
Provides-Extra: swap
Requires-Dist: psutil~=7.0; extra == "swap"
Dynamic: author
Dynamic: author-email
Dynamic: classifier
Dynamic: description
Dynamic: description-content-type
Dynamic: home-page
Dynamic: keywords
Dynamic: license-file
Dynamic: license-expression
Dynamic: maintainer
Dynamic: maintainer-email
Dynamic: provides-extra
Dynamic: requires-dist
Dynamic: requires-python
Dynamic: summary
